[
    {
        "placeId": "ChIJ3SjtxzWdLhMRC0sa2s_aElw",
        "website": "http://www.assisimuseodiocesano.it/",
        "index": 1,
        "utcOffset": 120,
        "longitude": 12.617478,
        "latitude": 43.070575,
        "rating": 4.7,
        "excerpt": "13th-century church with ornate friezes & statutes, plus the font where St Francis was baptized.",
        "detail_description": "The Cathedral of San Rufino is a 13th-century church located in Assisi, Italy. It is divided into two main churches, the Lower and Upper basilicas. The interior features ornate friezes, statues, and numerous chapels such as those dedicated to St. Mary Magdalene and St. Louis of Toulouse. The cathedral has an unmistakable Romanesque character with modern features added during the 16th century.",
        "imageKeys": [
            "ZJFoN48oKsAdlnDPqlTlvo39IEox8aY4",
            "SBywYuuuLMqAUURrIbjpukxRP0XhwuPe",
            "QYKBouahuCHakhjnNWzni1oOpGzvwVPp",
            "dkBZAk85XDpna7BCxUP0Z07vBJMirRap",
            "Ur4Wu9QYE7ssSZDp7PmAomSCXNGkAJ9W"
        ],
        "ratingCount": 5001,
        "openingPeriods": [
            {
                "open": {
                    "day": 0,
                    "time": "0700"
                },
                "close": {
                    "day": 0,
                    "time": "1930"
                }
            },
            {
                "open": {
                    "day": 1,
                    "time": "0700"
                },
                "close": {
                    "day": 1,
                    "time": "1930"
                }
            },
            {
                "open": {
                    "day": 2,
                    "time": "0700"
                },
                "close": {
                    "day": 2,
                    "time": "1930"
                }
            },
            {
                "open": {
                    "day": 3,
                    "time": "0700"
                },
                "close": {
                    "day": 3,
                    "time": "1930"
                }
            },
            {
                "open": {
                    "day": 4,
                    "time": "0700"
                },
                "close": {
                    "day": 4,
                    "time": "1930"
                }
            },
            {
                "open": {
                    "day": 5,
                    "time": "0700"
                },
                "close": {
                    "day": 5,
                    "time": "1930"
                }
            },
            {
                "open": {
                    "day": 6,
                    "time": "0700"
                },
                "close": {
                    "day": 6,
                    "time": "1930"
                }
            }
        ],
        "name": "Cathedral of San Rufino",
        "permanentlyClosed": false,
        "priceLevel": null,
        "phone": "+39 075 812283",
        "address": "Piazza San Rufino, 3, 06081 Assisi PG, Italy",
        "types": [
            "Catholic cathedral",
            "Sights & Landmarks",
            "Cathedral",
            "Catholic church",
            "Museum",
            "Churches & Cathedrals"
        ],
        "ratingDistribution": {
            "Google": {
                "1": 29,
                "2": 19,
                "3": 263,
                "4": 1039,
                "5": 3676
            }
        }
    },
    {
        "placeId": "ChIJqxAbJTSdLhMRnLdKcG-dBtw",
        "website": "http://www.assisisantachiara.it/",
        "index": 2,
        "utcOffset": 120,
        "longitude": 12.617006,
        "latitude": 43.068843,
        "rating": 4.8,
        "excerpt": "13th-century church with a striking pink-&-white facade housing the tomb of St Clare.",
        "detail_description": "Basilica di Santa Chiara is a 13th-century church in Assisi, Italy, featuring a striking pink-and-white facade. It was built to honor St. Clare shortly after her burial in 1253 and was consecrated in 1265 by Pope Clement IV. The basilica houses the tomb of St. Clare and also preserves the Crucifix of San Damiano, which spoke to St. Francis.",
        "imageKeys": [
            "TiDbuZDCG7fMhIENRHDuH79IPBtzMqQJ",
            "hCtOE6KJowYNK1TMfMYWxmMDwLRemvz4",
            "VbBn0dhCDkLAnXq7qciGCBhq0mBnl81H",
            "4ag6br8oK4EbVsBc5xcleqcJ3m4EwjKC",
            "c86TUPzOG635OBkryU9vWeZZbMqkTq0A"
        ],
        "ratingCount": 11899,
        "openingPeriods": [
            {
                "open": {
                    "day": 0,
                    "time": "0630"
                },
                "close": {
                    "day": 0,
                    "time": "1200"
                }
            },
            {
                "open": {
                    "day": 0,
                    "time": "1400"
                },
                "close": {
                    "day": 0,
                    "time": "1800"
                }
            },
            {
                "open": {
                    "day": 1,
                    "time": "0630"
                },
                "close": {
                    "day": 1,
                    "time": "1200"
                }
            },
            {
                "open": {
                    "day": 1,
                    "time": "1400"
                },
                "close": {
                    "day": 1,
                    "time": "1800"
                }
            },
            {
                "open": {
                    "day": 2,
                    "time": "0630"
                },
                "close": {
                    "day": 2,
                    "time": "1200"
                }
            },
            {
                "open": {
                    "day": 2,
                    "time": "1400"
                },
                "close": {
                    "day": 2,
                    "time": "1800"
                }
            },
            {
                "open": {
                    "day": 3,
                    "time": "0630"
                },
                "close": {
                    "day": 3,
                    "time": "1200"
                }
            },
            {
                "open": {
                    "day": 3,
                    "time": "1400"
                },
                "close": {
                    "day": 3,
                    "time": "1800"
                }
            },
            {
                "open": {
                    "day": 4,
                    "time": "0630"
                },
                "close": {
                    "day": 4,
                    "time": "1200"
                }
            },
            {
                "open": {
                    "day": 4,
                    "time": "1400"
                },
                "close": {
                    "day": 4,
                    "time": "1800"
                }
            },
            {
                "open": {
                    "day": 5,
                    "time": "0630"
                },
                "close": {
                    "day": 5,
                    "time": "1200"
                }
            },
            {
                "open": {
                    "day": 5,
                    "time": "1400"
                },
                "close": {
                    "day": 5,
                    "time": "1800"
                }
            },
            {
                "open": {
                    "day": 6,
                    "time": "0630"
                },
                "close": {
                    "day": 6,
                    "time": "1200"
                }
            },
            {
                "open": {
                    "day": 6,
                    "time": "1400"
                },
                "close": {
                    "day": 6,
                    "time": "1800"
                }
            }
        ],
        "name": "Basilica di Santa Chiara",
        "permanentlyClosed": false,
        "priceLevel": null,
        "phone": "+39 075 812216",
        "address": "P.za Santa Chiara, 1, 06081 Assisi PG, Italy",
        "types": [
            "Basilica",
            "Sights & Landmarks",
            "Architectural Buildings",
            "Sacred & Religious Sites",
            "Historic Sites",
            "Churches & Cathedrals"
        ],
        "ratingDistribution": {
            "Google": {
                "1": 69,
                "2": 38,
                "3": 324,
                "4": 1839,
                "5": 9678
            }
        }
    },
    {
        "placeId": "ChIJcdct-UmdLhMRS10zlKEnqjY",
        "website": "https://www.visit-assisi.it/monumenti-e-luoghi-dinteresse-2/siti-medievali/rocca-maggiore-2/",
        "index": 3,
        "utcOffset": 120,
        "longitude": 12.6156,
        "latitude": 43.073013,
        "rating": 4.5,
        "excerpt": "Large, dramatic medieval fortress with panoramic views & historical relics on display.",
        "detail_description": "Rocca Maggiore is a grand medieval fortress that has loomed over Assisi for over 800 years. The castle offers panoramic views and houses historical artifacts. Nearby, visitors can explore the Roman Amphitheatre, now a public garden, and the Basilica di Santa Chiara, where St. Clare of Assisi is buried. Eremo dell Carceri, a serene monastery nestled in the trees just outside of town, provides another peaceful retreat.",
        "imageKeys": [
            "osSUHBTBG9TSCrAJrWNMxhODAoceLwmG",
            "472ICWzxlPyXO7l3chgy61mDp6bhSXWq",
            "4FQN5ZRcsYLog2tdi8v7zrrqnMNwSBW6",
            "xXNh46QGMtzrYUvegHPkIMIkVLtWKgoM",
            "LdsY7VDBr4JbTkCfFeuH5WLwHHIWumcg"
        ],
        "ratingCount": 4647,
        "openingPeriods": [
            {
                "open": {
                    "day": 0,
                    "time": "1000"
                },
                "close": {
                    "day": 0,
                    "time": "1915"
                }
            },
            {
                "open": {
                    "day": 1,
                    "time": "1000"
                },
                "close": {
                    "day": 1,
                    "time": "1915"
                }
            },
            {
                "open": {
                    "day": 2,
                    "time": "1000"
                },
                "close": {
                    "day": 2,
                    "time": "1915"
                }
            },
            {
                "open": {
                    "day": 3,
                    "time": "1000"
                },
                "close": {
                    "day": 3,
                    "time": "1915"
                }
            },
            {
                "open": {
                    "day": 4,
                    "time": "1000"
                },
                "close": {
                    "day": 4,
                    "time": "1915"
                }
            },
            {
                "open": {
                    "day": 5,
                    "time": "1000"
                },
                "close": {
                    "day": 5,
                    "time": "1915"
                }
            },
            {
                "open": {
                    "day": 6,
                    "time": "1000"
                },
                "close": {
                    "day": 6,
                    "time": "1915"
                }
            }
        ],
        "name": "Rocca Maggiore",
        "permanentlyClosed": false,
        "priceLevel": null,
        "phone": "+39 075 813 8680",
        "address": "Via della Rocca, 06081 Assisi PG, Italy",
        "types": [
            "Fortress",
            "Sights & Landmarks",
            "Castles"
        ],
        "ratingDistribution": {
            "Google": {
                "1": 67,
                "2": 76,
                "3": 369,
                "4": 1123,
                "5": 3045
            }
        }
    },
    {
        "placeId": "ChIJ8SRwUjOdLhMRrOP82H0amNA",
        "website": null,
        "index": 4,
        "utcOffset": 120,
        "longitude": 12.619673,
        "latitude": 43.070631,
        "rating": null,
        "excerpt": "Assisi is a hill town in central Italy’s Umbria region. It was the birthplace of St. Francis (1181–1226), one of Italy’s patron saints. The Basilica of St. Francis is a massive, 2-level church, consecrated in 1253. Its 13th-century frescoes portraying the life of St. Francis have been attributed to Giotto and Cimabue, among others. The crypt houses the saint’s stone sarcophagus.",
        "detail_description": "Assisi, a picturesque hill town in Umbria, Italy, is renowned as the birthplace of St. Francis, one of Italy's patron saints. The Basilica of St. Francis stands as a monumental church with 13th-century frescoes attributed to renowned artists like Giotto and Cimabue. The town hosts the Calendimaggio festival every May to celebrate spring's arrival with medieval processions and musical performances.",
        "imageKeys": [
            "DoBefGoHwOlHzOFENHljxQH0AHau7eCx",
            "sNd7M9tV9NqO8EPr7mBQgJEzZ6DBbnvU",
            "hvARy97I2z7s5UwsfJdPNHmkbIHIBSEg",
            "8fohpKntR4RvxEuQl9XKsXx9O5gWdV8M",
            "i9jHPs303CKDpm8O3tpumPsCsFnpJNGC"
        ],
        "ratingCount": null,
        "openingPeriods": null,
        "name": "Assisi",
        "permanentlyClosed": false,
        "priceLevel": null,
        "phone": null,
        "address": "06081 Province of Perugia, Italy",
        "types": [],
        "ratingDistribution": {
            "Google": {
                "1": 0,
                "2": 0,
                "3": 0,
                "4": 0,
                "5": 0
            }
        }
    },
    {
        "placeId": "ChIJaW_JbzadLhMRYBqOmvJm9m4",
        "website": null,
        "index": 5,
        "utcOffset": 120,
        "longitude": 12.614743,
        "latitude": 43.071373,
        "rating": 4.6,
        "excerpt": "14th-century, Gothic-style church built from a former Greek temple & still retaining its façade.",
        "detail_description": "The Church of Santa Maria sopra Minerva in Assisi is a 14th-century Gothic-style church that was built from a former Greek temple, the Temple of Minerva. The church still retains the facade of the ancient temple, which dates back to the 1st century BC. Located in Piazza del Comune, this historic site also houses Roman remains near the altar and offers access to the ancient forum below through the nearby Civic Museum.",
        "imageKeys": [
            "RoaEHnftEpy6ag754ZJCcMAQ9UHcOmZF",
            "4bRVlgtkOIFsDeECgpmBxdO26bPn71a4",
            "49FjluUoSeSQOKE0FxNwkGteOffcpQV2",
            "Wfs52aIVmaNdubs0DhORKIquDvyttIPc",
            "kMdol7SwKUk2CycnsBsrnmOo71A7Fjnd"
        ],
        "ratingCount": 708,
        "openingPeriods": [
            {
                "open": {
                    "day": 0,
                    "time": "0800"
                },
                "close": {
                    "day": 0,
                    "time": "2000"
                }
            },
            {
                "open": {
                    "day": 1,
                    "time": "0800"
                },
                "close": {
                    "day": 1,
                    "time": "2000"
                }
            },
            {
                "open": {
                    "day": 2,
                    "time": "0800"
                },
                "close": {
                    "day": 2,
                    "time": "2000"
                }
            },
            {
                "open": {
                    "day": 3,
                    "time": "0800"
                },
                "close": {
                    "day": 3,
                    "time": "2000"
                }
            },
            {
                "open": {
                    "day": 4,
                    "time": "0800"
                },
                "close": {
                    "day": 4,
                    "time": "2000"
                }
            },
            {
                "open": {
                    "day": 5,
                    "time": "0800"
                },
                "close": {
                    "day": 5,
                    "time": "2000"
                }
            },
            {
                "open": {
                    "day": 6,
                    "time": "0800"
                },
                "close": {
                    "day": 6,
                    "time": "2000"
                }
            }
        ],
        "name": "Church of Santa Maria sopra Minerva in Assisi",
        "permanentlyClosed": false,
        "priceLevel": null,
        "phone": "+39 075 812361",
        "address": "Piazza del Comune, 14, 06081 Assisi PG, Italy",
        "types": [
            "Catholic church",
            "Sights & Landmarks",
            "Architectural Buildings"
        ],
        "ratingDistribution": {
            "Google": {
                "1": 3,
                "2": 2,
                "3": 35,
                "4": 161,
                "5": 511
            }
        }
    },
    {
        "placeId": "ChIJ5cO0QEedLhMR2DfH3U4y3kc",
        "website": "https://www.sanfrancescoassisi.org/",
        "index": 6,
        "utcOffset": 120,
        "longitude": 12.6054,
        "latitude": 43.074971,
        "rating": 4.9,
        "excerpt": "Landmark hillside Gothic church & site of Christian pilgrimage, decorated with noted medieval art.",
        "detail_description": "The Papal Basilica and Sacred Convent of Saint Francis in Assisi is an iconic Gothic church and a major Christian pilgrimage site. This UNESCO World Heritage Site consists of the Upper Basilica and the Lower Basilica, adorned with medieval art. The basilica also features smaller chapels like those dedicated to St Mary Magdalene and St Louis of Toulouse. It's recommended to use an audio guide to explore the rich history behind this impressive structure.",
        "imageKeys": [
            "Pu2u0ij9N6w4unqnvvxBzs2qopCEIzKy",
            "i1McEXHiBIyc0QXPrbZJRS0HzvgQY34Z",
            "fFwnCR3cC4Mt5SYRd7sY4OKDziNvp1vs",
            "YJQoVauVYmppxyEgKyHrxukaG78nej8K",
            "o8CtBFFnShziTXpvUh8qvNXEjYFSWRje"
        ],
        "ratingCount": 45406,
        "openingPeriods": [
            {
                "open": {
                    "day": 0,
                    "time": "0600"
                },
                "close": {
                    "day": 0,
                    "time": "1900"
                }
            },
            {
                "open": {
                    "day": 1,
                    "time": "0600"
                },
                "close": {
                    "day": 1,
                    "time": "1900"
                }
            },
            {
                "open": {
                    "day": 2,
                    "time": "0600"
                },
                "close": {
                    "day": 2,
                    "time": "1900"
                }
            },
            {
                "open": {
                    "day": 3,
                    "time": "0600"
                },
                "close": {
                    "day": 3,
                    "time": "1900"
                }
            },
            {
                "open": {
                    "day": 4,
                    "time": "0600"
                },
                "close": {
                    "day": 4,
                    "time": "1900"
                }
            },
            {
                "open": {
                    "day": 5,
                    "time": "0600"
                },
                "close": {
                    "day": 5,
                    "time": "1900"
                }
            },
            {
                "open": {
                    "day": 6,
                    "time": "0600"
                },
                "close": {
                    "day": 6,
                    "time": "1900"
                }
            }
        ],
        "name": "Papal Basilica and Sacred Convent of Saint Francis in Assisi",
        "permanentlyClosed": false,
        "priceLevel": null,
        "phone": "+39 075 819001",
        "address": "Piazza Inferiore di S. Francesco, 2, 06081 Assisi PG, Italy",
        "types": [
            "Basilica",
            "Sights & Landmarks",
            "Catholic church",
            "Churches & Cathedrals"
        ],
        "ratingDistribution": {
            "Google": {
                "1": 277,
                "2": 129,
                "3": 538,
                "4": 3572,
                "5": 41046
            }
        }
    },
    {
        "placeId": "ChIJky1EezadLhMRnw1qSxvPWUM",
        "website": "https://www.assisiofm.it/chiesa-nuova-assisi-101-1.html",
        "index": 7,
        "utcOffset": 120,
        "longitude": 12.615248,
        "latitude": 43.070412,
        "rating": 4.7,
        "excerpt": "17th-century church associated with St. Francis of Assisi, home to a Franciscan museum & library.",
        "detail_description": "Chiesa Nuova di San Francesco Convertito is a 17th-century church in Assisi, Italy, closely associated with St. Francis of Assisi. It is built on the site of his father's house and is believed to be where he was locked up by his father for choosing a life of poverty. The church also houses a Franciscan museum and library.",
        "imageKeys": [
            "U1o8WKGVQI7ILc2kHJlghLHWADV7NKDA",
            "Zlolnk8d1bERz7zud5trAYCcHSk2gIEz",
            "Y7kgA2U3m4VvHe6LbhqSQh0SqEha9Qb0",
            "vfmKmz6jHc52AAQ3B4uPfU6HWIoIM8Nq",
            "oiLkXAM63HE59qWtpwT2x7DSJ2p0B9s5"
        ],
        "ratingCount": 285,
        "openingPeriods": [
            {
                "open": {
                    "day": 0,
                    "time": "0800"
                },
                "close": {
                    "day": 0,
                    "time": "1230"
                }
            },
            {
                "open": {
                    "day": 0,
                    "time": "1430"
                },
                "close": {
                    "day": 0,
                    "time": "1915"
                }
            },
            {
                "open": {
                    "day": 1,
                    "time": "0800"
                },
                "close": {
                    "day": 1,
                    "time": "1230"
                }
            },
            {
                "open": {
                    "day": 1,
                    "time": "1430"
                },
                "close": {
                    "day": 1,
                    "time": "1915"
                }
            },
            {
                "open": {
                    "day": 2,
                    "time": "0800"
                },
                "close": {
                    "day": 2,
                    "time": "1230"
                }
            },
            {
                "open": {
                    "day": 2,
                    "time": "1430"
                },
                "close": {
                    "day": 2,
                    "time": "1915"
                }
            },
            {
                "open": {
                    "day": 3,
                    "time": "0800"
                },
                "close": {
                    "day": 3,
                    "time": "1230"
                }
            },
            {
                "open": {
                    "day": 3,
                    "time": "1430"
                },
                "close": {
                    "day": 3,
                    "time": "1915"
                }
            },
            {
                "open": {
                    "day": 4,
                    "time": "0800"
                },
                "close": {
                    "day": 4,
                    "time": "1230"
                }
            },
            {
                "open": {
                    "day": 4,
                    "time": "1430"
                },
                "close": {
                    "day": 4,
                    "time": "1915"
                }
            },
            {
                "open": {
                    "day": 5,
                    "time": "0800"
                },
                "close": {
                    "day": 5,
                    "time": "1230"
                }
            },
            {
                "open": {
                    "day": 5,
                    "time": "1430"
                },
                "close": {
                    "day": 5,
                    "time": "1915"
                }
            },
            {
                "open": {
                    "day": 6,
                    "time": "0800"
                },
                "close": {
                    "day": 6,
                    "time": "1230"
                }
            },
            {
                "open": {
                    "day": 6,
                    "time": "1430"
                },
                "close": {
                    "day": 6,
                    "time": "1915"
                }
            }
        ],
        "name": "Chiesa Nuova di San Francesco Convertito",
        "permanentlyClosed": false,
        "priceLevel": null,
        "phone": "+39 075 812339",
        "address": "Piazza Chiesa Nuova, 7, 06081 Assisi PG, Italy",
        "types": [
            "Catholic church"
        ],
        "ratingDistribution": {
            "Google": {
                "1": 1,
                "2": 3,
                "3": 14,
                "4": 55,
                "5": 212
            }
        }
    },
    {
        "placeId": "ChIJla4fbzadLhMRvTRvOySlUYI",
        "website": null,
        "index": 8,
        "utcOffset": 120,
        "longitude": 12.614849,
        "latitude": 43.071143,
        "rating": null,
        "excerpt": null,
        "detail_description": "Piazza del Comune in Assisi is a charming square surrounded by historic landmarks, offering visitors a perfect spot to unwind and immerse themselves in the town's ambiance. The square is encircled by notable buildings such as the Palazzo del Capitano del Popolo and the ancient Temple of Minerva, which traces its origins back to the 1st century BC.",
        "imageKeys": [],
        "ratingCount": null,
        "openingPeriods": null,
        "name": "Piazza del Comune",
        "permanentlyClosed": false,
        "priceLevel": null,
        "phone": null,
        "address": "06081 Assisi PG, Italy",
        "types": [
            "Town square"
        ],
        "ratingDistribution": {
            "Google": {
                "1": 0,
                "2": 0,
                "3": 0,
                "4": 0,
                "5": 0
            }
        }
    },
    {
        "placeId": "ChIJz8dioi2dLhMRI9RBQWI3kL8",
        "website": "http://www.santuariosandamiano.org/",
        "index": 9,
        "utcOffset": 120,
        "longitude": 12.618109,
        "latitude": 43.061532,
        "rating": 4.8,
        "excerpt": "Modest, rustic-style 12th-century church & cloisters, said to be where Christ spoke to St Francis.",
        "detail_description": "San Damiano is a 12th-century church and cloisters located in Assisi, surrounded by terraced olive groves. It holds great significance as the place where St. Francis received a message from God to rebuild his house. This sanctuary embodies the virtues and values of St. Francis, representing an important part of his life.",
        "imageKeys": [
            "8LARBNd9mKuSzEKbxQPqtMKxTCqXLLZ2",
            "BPznR1JM0Nmr1g7asqKobRgT6kdXteXX",
            "x1rkVY34Yjeqdf6CiHLBcuKIQ6n1Y76A",
            "YtIFBdODIOM7u0xQP9DSBckeMS1YrAav",
            "t7GJnFm9OJub1umTJudgdkvxJGW600VI"
        ],
        "ratingCount": 7043,
        "openingPeriods": [
            {
                "open": {
                    "day": 0,
                    "time": "1000"
                },
                "close": {
                    "day": 0,
                    "time": "1200"
                }
            },
            {
                "open": {
                    "day": 0,
                    "time": "1400"
                },
                "close": {
                    "day": 0,
                    "time": "1800"
                }
            },
            {
                "open": {
                    "day": 1,
                    "time": "1000"
                },
                "close": {
                    "day": 1,
                    "time": "1200"
                }
            },
            {
                "open": {
                    "day": 1,
                    "time": "1400"
                },
                "close": {
                    "day": 1,
                    "time": "1800"
                }
            },
            {
                "open": {
                    "day": 2,
                    "time": "1000"
                },
                "close": {
                    "day": 2,
                    "time": "1200"
                }
            },
            {
                "open": {
                    "day": 2,
                    "time": "1400"
                },
                "close": {
                    "day": 2,
                    "time": "1800"
                }
            },
            {
                "open": {
                    "day": 3,
                    "time": "1000"
                },
                "close": {
                    "day": 3,
                    "time": "1200"
                }
            },
            {
                "open": {
                    "day": 3,
                    "time": "1400"
                },
                "close": {
                    "day": 3,
                    "time": "1800"
                }
            },
            {
                "open": {
                    "day": 4,
                    "time": "1000"
                },
                "close": {
                    "day": 4,
                    "time": "1200"
                }
            },
            {
                "open": {
                    "day": 4,
                    "time": "1400"
                },
                "close": {
                    "day": 4,
                    "time": "1800"
                }
            },
            {
                "open": {
                    "day": 5,
                    "time": "1000"
                },
                "close": {
                    "day": 5,
                    "time": "1200"
                }
            },
            {
                "open": {
                    "day": 5,
                    "time": "1400"
                },
                "close": {
                    "day": 5,
                    "time": "1800"
                }
            },
            {
                "open": {
                    "day": 6,
                    "time": "1000"
                },
                "close": {
                    "day": 6,
                    "time": "1200"
                }
            },
            {
                "open": {
                    "day": 6,
                    "time": "1400"
                },
                "close": {
                    "day": 6,
                    "time": "1800"
                }
            }
        ],
        "name": "San Damiano",
        "permanentlyClosed": false,
        "priceLevel": null,
        "phone": "+39 075 812273",
        "address": "Via San Damiano, 7, 06081 Assisi PG, Italy",
        "types": [
            "Catholic church",
            "Sights & Landmarks",
            "Church",
            "Shrine",
            "Sacred & Religious Sites",
            "Historic Sites"
        ],
        "ratingDistribution": {
            "Google": {
                "1": 44,
                "2": 16,
                "3": 99,
                "4": 651,
                "5": 6263
            }
        }
    },
    {
        "placeId": "ChIJ_5lGiEydLhMRlZtRd9Czbz0",
        "website": "https://www.fondoambiente.it/luoghi/bosco-di-san-francesco?utm_source=gmb&utm_medium=referral&utm_campaign=bosco",
        "index": 10,
        "utcOffset": 120,
        "longitude": 12.614999,
        "latitude": 43.082159,
        "rating": 4.5,
        "excerpt": null,
        "detail_description": "Bosco di San Francesco, managed by the Italian National Trust (FAI), is a serene woodland area near the Basilica of St. Francis in Umbria. Covering about 64 hectares, it offers visitors a chance to explore ancient woodlands, olive groves, and walk along the Tescio River on a network of trails.",
        "imageKeys": [
            "1LcFtL3t2Xr69iaBf8wwBUu6FqfX6XiH",
            "gTxbTyTp3WeNv5FXPTmMCgyijHkwYDrK",
            "vHHASs0KUMp2Jp2mI0B8B7jJ5GZDUqOB",
            "oYEpKekqMFSOgGU5dhjlPrpuVooFJuO4"
        ],
        "ratingCount": 1238,
        "openingPeriods": [
            {
                "open": {
                    "day": 0,
                    "time": "1000"
                },
                "close": {
                    "day": 0,
                    "time": "1900"
                }
            },
            {
                "open": {
                    "day": 2,
                    "time": "1000"
                },
                "close": {
                    "day": 2,
                    "time": "1900"
                }
            },
            {
                "open": {
                    "day": 3,
                    "time": "1000"
                },
                "close": {
                    "day": 3,
                    "time": "1900"
                }
            },
            {
                "open": {
                    "day": 4,
                    "time": "1000"
                },
                "close": {
                    "day": 4,
                    "time": "1900"
                }
            },
            {
                "open": {
                    "day": 5,
                    "time": "1000"
                },
                "close": {
                    "day": 5,
                    "time": "1900"
                }
            },
            {
                "open": {
                    "day": 6,
                    "time": "1000"
                },
                "close": {
                    "day": 6,
                    "time": "1900"
                }
            }
        ],
        "name": "Bosco di San Francesco",
        "permanentlyClosed": false,
        "priceLevel": null,
        "phone": "+39 075 813157",
        "address": "Via Ponte dei Galli, 1, 06081 Assisi PG, Italy",
        "types": [
            "Nature & Parks",
            "Historical landmark",
            "Nature & Wildlife Areas"
        ],
        "ratingDistribution": {
            "Google": {
                "1": 34,
                "2": 20,
                "3": 78,
                "4": 248,
                "5": 859
            }
        }
    },
    {
        "placeId": "ChIJfZOFbzadLhMRIAFWJ0aiPMQ",
        "website": "http://www.comune.assisi.pg.it/",
        "index": 11,
        "utcOffset": 120,
        "longitude": 12.61502,
        "latitude": 43.071064,
        "rating": 4.7,
        "excerpt": null,
        "detail_description": "Piazza del Comune in Assisi is a historic square that dates back to Roman times and flourished as a bustling trade center during the Middle Ages. The square boasts an array of remarkable monuments, including the ancient Roman Temple of Minerva, which has been transformed into a church, the Fountain of the Lions, and the tabernacle. Visitors can soak up the vibrant atmosphere by sitting on the stone steps of the Temple of Minerva while indulging in some gelato and observing local life.",
        "imageKeys": [
            "Xi2Or8PZPSHBaCtO8WfTNHw9l803i32a",
            "TIoRfkLOIczlRtiuITWMP1ceLhEYvyKj",
            "CDaqJ751bSqKTS6D0jI5YKpw5UCOQMyB",
            "oquCia3nopgCiNNNl5gNjXYkjVOo3DsW",
            "08yGoCfSkt6RPtJ2To1OR6OvghL793aV"
        ],
        "ratingCount": 4119,
        "openingPeriods": [
            {
                "open": {
                    "day": 0,
                    "time": "0000"
                }
            },
            {
                "open": {
                    "day": 1,
                    "time": "0000"
                }
            },
            {
                "open": {
                    "day": 2,
                    "time": "0000"
                }
            },
            {
                "open": {
                    "day": 3,
                    "time": "0000"
                }
            },
            {
                "open": {
                    "day": 4,
                    "time": "0000"
                }
            },
            {
                "open": {
                    "day": 5,
                    "time": "0000"
                }
            },
            {
                "open": {
                    "day": 6,
                    "time": "0000"
                }
            }
        ],
        "name": "Piazza del Comune",
        "permanentlyClosed": false,
        "priceLevel": null,
        "phone": "+39 075 813 8680",
        "address": "1, 06081 Assisi PG, Italy",
        "types": [
            "Sights & Landmarks",
            "Points of Interest & Landmarks"
        ],
        "ratingDistribution": {
            "Google": {
                "1": 40,
                "2": 25,
                "3": 188,
                "4": 806,
                "5": 3064
            }
        }
    },
    {
        "placeId": "ChIJ3xHcBTidLhMRW7eL_zahxWE",
        "website": null,
        "index": 12,
        "utcOffset": 120,
        "longitude": 12.608832,
        "latitude": 43.073186,
        "rating": null,
        "excerpt": null,
        "detail_description": "Via San Francesco, along with Il Corso, is one of the bustling main streets in the area. It is lined with various shops selling religious souvenirs and memorabilia. While some may find it difficult to find high-quality items here, there are still unique finds such as charming Francis-inspired leather sandal magnets that catch the eye of many visitors.",
        "imageKeys": [
            "d7ZrJC2p075JvmHdU9gIrWe8TI7aZVyR",
            "dpLDyu6JQq865NGox7Zi5UiXL6vo6dGE",
            "bS1pC0LyamdBW4Myw0VVHRcjev8K5ri3",
            "yrPID1raV0l1SB30okrGQP5Mf5NIj1yF",
            "M1wTyaGDSMm8zv2vAyOqOnqVtHOcjUwH"
        ],
        "ratingCount": null,
        "openingPeriods": null,
        "name": "Via San Francesco",
        "permanentlyClosed": false,
        "priceLevel": null,
        "phone": null,
        "address": "06081 Assisi PG, Italy",
        "types": [
            "Sights & Landmarks",
            "Points of Interest & Landmarks"
        ],
        "ratingDistribution": {
            "Google": {
                "1": 0,
                "2": 0,
                "3": 0,
                "4": 0,
                "5": 0
            }
        }
    },
    {
        "placeId": "ChIJ7UwxhjidLhMRx2AF61anwYQ",
        "website": "https://www.sanfrancescoassisi.org/fondazione/ita/shownews.php?idNews=574&zone=WFOnotizie",
        "index": 13,
        "utcOffset": 120,
        "longitude": 12.607165,
        "latitude": 43.073001,
        "rating": 4.7,
        "excerpt": null,
        "detail_description": "Porta San Francesco is an ancient entrance to Perugia, modified in the 15th century and adorned with frescoes discovered in 1911. It's part of the remaining gates of the medieval city walls, representing the entrance to Assisi's historic center. Visitors describe it as a beautiful door with a medieval touch and a wonderful place exuding peace and serenity.",
        "imageKeys": [
            "Jsb3Lqx1ve2RdMmHrcDiTY377AXCbdBu",
            "0D5hy0T1EqXa5U0OxJTCNXejMaSkvbuL",
            "JjNNDgGg97pPfjtgESFAvv62kJrsFGOf"
        ],
        "ratingCount": 109,
        "openingPeriods": [
            {
                "open": {
                    "day": 0,
                    "time": "0000"
                }
            },
            {
                "open": {
                    "day": 1,
                    "time": "0000"
                }
            },
            {
                "open": {
                    "day": 2,
                    "time": "0000"
                }
            },
            {
                "open": {
                    "day": 3,
                    "time": "0000"
                }
            },
            {
                "open": {
                    "day": 4,
                    "time": "0000"
                }
            },
            {
                "open": {
                    "day": 5,
                    "time": "0000"
                }
            },
            {
                "open": {
                    "day": 6,
                    "time": "0000"
                }
            }
        ],
        "name": "Porta San Francesco",
        "permanentlyClosed": false,
        "priceLevel": null,
        "phone": null,
        "address": "Viale Guglielmo Marconi, 2, 06081 Assisi PG, Italy",
        "types": [
            "Historical landmark",
            "Sights & Landmarks",
            "Historic Walking Areas"
        ],
        "ratingDistribution": {
            "Google": {
                "1": 0,
                "2": 1,
                "3": 2,
                "4": 25,
                "5": 81
            }
        }
    },
    {
        "placeId": "ChIJz9rV7TedLhMR3fEA2SYkBo8",
        "website": null,
        "index": 14,
        "utcOffset": 120,
        "longitude": 12.610742,
        "latitude": 43.072402,
        "rating": 4.6,
        "excerpt": null,
        "detail_description": "The Portico of Monte Frumentario in Assisi is a must-visit spot, offering a glimpse into the enchanting world of Santa Claus and his elves. The area boasts stunning ancient architecture and picturesque landscapes that showcase the beauty of Umbria. Visitors can take leisurely strolls, savor coffee with breathtaking views, and immerse themselves in the fascinating history of this charming village. While exploring the Basilica nearby is highly recommended, travelers should be cautious of local restaurants with questionable practices.",
        "imageKeys": [
            "e9Acg0FEyHmsTGwv31AD2G11xKcDZwby",
            "GG8FuNVZsBAdiMPrz0x29SxNOJfSVSkh",
            "uVqMbJr0oqDSTMJ4ArZP4TU9NnIUbJVd"
        ],
        "ratingCount": 709,
        "openingPeriods": [
            {
                "open": {
                    "day": 0,
                    "time": "0000"
                }
            },
            {
                "open": {
                    "day": 1,
                    "time": "0000"
                }
            },
            {
                "open": {
                    "day": 2,
                    "time": "0000"
                }
            },
            {
                "open": {
                    "day": 3,
                    "time": "0000"
                }
            },
            {
                "open": {
                    "day": 4,
                    "time": "0000"
                }
            },
            {
                "open": {
                    "day": 5,
                    "time": "0000"
                }
            },
            {
                "open": {
                    "day": 6,
                    "time": "0000"
                }
            }
        ],
        "name": "Portico of Monte Frumentario",
        "permanentlyClosed": false,
        "priceLevel": null,
        "phone": null,
        "address": "Via San Francesco, 5A, 06081 Assisi PG, Italy",
        "types": [
            "Historical landmark"
        ],
        "ratingDistribution": {
            "Google": {
                "1": 5,
                "2": 7,
                "3": 41,
                "4": 156,
                "5": 500
            }
        }
    },
    {
        "placeId": "ChIJ__joWG2dLhMRkBI9lGJZtQo",
        "website": "http://www.saioassisi.it/",
        "index": 15,
        "utcOffset": 120,
        "longitude": 12.586102,
        "latitude": 43.076696,
        "rating": 4.8,
        "excerpt": null,
        "detail_description": "At Cantina SAIO in Assisi, visitors can indulge in a delightful wine tasting experience paired with a charming picnic. The friendly staff, particularly Agnese, are fluent in English and provide insightful information about the local wines and olive oils. Guests can enjoy reasonably priced tastings while soaking up stunning views of Assisi at sunset.",
        "imageKeys": [
            "xiMZZMUvq5z4K514RBLtWOclsMlobX5F",
            "cA2UbYvOPuVAR0qBFcvSbNTvCwLEPJ7f",
            "NzGI56la4EmXWSzbjtva2PVfK9fLEzGs",
            "q3m7wz9QQSEdGBMwIryNMLvBIb35Y3bM",
            "h3f1uTrmw67y2OMzdasflewWQ3YNP0T1"
        ],
        "ratingCount": 88,
        "openingPeriods": [
            {
                "open": {
                    "day": 0,
                    "time": "1000"
                },
                "close": {
                    "day": 0,
                    "time": "1230"
                }
            },
            {
                "open": {
                    "day": 1,
                    "time": "1000"
                },
                "close": {
                    "day": 1,
                    "time": "1230"
                }
            },
            {
                "open": {
                    "day": 1,
                    "time": "1600"
                },
                "close": {
                    "day": 1,
                    "time": "1830"
                }
            },
            {
                "open": {
                    "day": 2,
                    "time": "1000"
                },
                "close": {
                    "day": 2,
                    "time": "1230"
                }
            },
            {
                "open": {
                    "day": 2,
                    "time": "1600"
                },
                "close": {
                    "day": 2,
                    "time": "1830"
                }
            },
            {
                "open": {
                    "day": 4,
                    "time": "1000"
                },
                "close": {
                    "day": 4,
                    "time": "1230"
                }
            },
            {
                "open": {
                    "day": 4,
                    "time": "1600"
                },
                "close": {
                    "day": 4,
                    "time": "1830"
                }
            },
            {
                "open": {
                    "day": 5,
                    "time": "1000"
                },
                "close": {
                    "day": 5,
                    "time": "1230"
                }
            },
            {
                "open": {
                    "day": 5,
                    "time": "1600"
                },
                "close": {
                    "day": 5,
                    "time": "1830"
                }
            },
            {
                "open": {
                    "day": 6,
                    "time": "1000"
                },
                "close": {
                    "day": 6,
                    "time": "1230"
                }
            },
            {
                "open": {
                    "day": 6,
                    "time": "1600"
                },
                "close": {
                    "day": 6,
                    "time": "1830"
                }
            }
        ],
        "name": "Cantina SAIO Assisi Degustazione vino, olio e prodotti tipici",
        "permanentlyClosed": false,
        "priceLevel": null,
        "phone": "+39 335 837 4784",
        "address": "Via Campiglione, 94/A, 06081 Assisi PG, Italy",
        "types": [
            "Winery",
            "Food & Drink",
            "Wineries & Vineyards"
        ],
        "ratingDistribution": {
            "Google": {
                "1": 2,
                "2": 0,
                "3": 1,
                "4": 12,
                "5": 75
            }
        }
    },
    {
        "placeId": "ChIJj3K0yTWdLhMR4NBukBpIu_E",
        "website": "https://www.assisimuseodiocesano.it/",
        "index": 16,
        "utcOffset": 120,
        "longitude": 12.617807,
        "latitude": 43.070154,
        "rating": 4.9,
        "excerpt": null,
        "detail_description": "The Assisi Diocesan Museum, established in 1941 by Bishop Giuseppe Placido Niccolini, offers a fascinating journey through nine sections showcasing over a hundred exhibits. Visitors can explore archaeological displays in the Corridor, admire detached frescoes in the Master of St. Clare room, and marvel at the polyptych of San Rufino in the Nicolo Alunno room. The museum also features the Crypt of San Rufino with its symbols of the four evangelists.",
        "imageKeys": [
            "iDQmblBw2v8necE6B3693EPjQQO5PRc4",
            "OLRhWDQ31jcOJ3CKsb2cjWDmI3ihFFNO",
            "YnBFxiAvHu6V9b2sUfxQ6MhYgbfz8qK5"
        ],
        "ratingCount": 37,
        "openingPeriods": [
            {
                "open": {
                    "day": 0,
                    "time": "1100"
                },
                "close": {
                    "day": 0,
                    "time": "1800"
                }
            },
            {
                "open": {
                    "day": 1,
                    "time": "1000"
                },
                "close": {
                    "day": 1,
                    "time": "1300"
                }
            },
            {
                "open": {
                    "day": 1,
                    "time": "1500"
                },
                "close": {
                    "day": 1,
                    "time": "1800"
                }
            },
            {
                "open": {
                    "day": 2,
                    "time": "1000"
                },
                "close": {
                    "day": 2,
                    "time": "1300"
                }
            },
            {
                "open": {
                    "day": 2,
                    "time": "1500"
                },
                "close": {
                    "day": 2,
                    "time": "1800"
                }
            },
            {
                "open": {
                    "day": 3,
                    "time": "1000"
                },
                "close": {
                    "day": 3,
                    "time": "1300"
                }
            },
            {
                "open": {
                    "day": 3,
                    "time": "1500"
                },
                "close": {
                    "day": 3,
                    "time": "1800"
                }
            },
            {
                "open": {
                    "day": 4,
                    "time": "1000"
                },
                "close": {
                    "day": 4,
                    "time": "1300"
                }
            },
            {
                "open": {
                    "day": 4,
                    "time": "1500"
                },
                "close": {
                    "day": 4,
                    "time": "1800"
                }
            },
            {
                "open": {
                    "day": 5,
                    "time": "1000"
                },
                "close": {
                    "day": 5,
                    "time": "1300"
                }
            },
            {
                "open": {
                    "day": 5,
                    "time": "1500"
                },
                "close": {
                    "day": 5,
                    "time": "1800"
                }
            },
            {
                "open": {
                    "day": 6,
                    "time": "1000"
                },
                "close": {
                    "day": 6,
                    "time": "1800"
                }
            }
        ],
        "name": "Assisi Diocesan Museum",
        "permanentlyClosed": false,
        "priceLevel": null,
        "phone": "+39 075 812712",
        "address": "Piazza San Rufino, 3, 06081 Assisi PG, Italy",
        "types": [
            "Museum",
            "Ancient Ruins",
            "Sacred & Religious Sites",
            "Historic Sites",
            "Art Museums",
            "Points of Interest & Landmarks"
        ],
        "ratingDistribution": {
            "Google": {
                "1": 0,
                "2": 0,
                "3": 0,
                "4": 5,
                "5": 32
            }
        }
    },
    {
        "placeId": "ChIJUaIVbjadLhMRQ-01JPSHvQ8",
        "website": null,
        "index": 17,
        "utcOffset": 120,
        "longitude": 12.615054,
        "latitude": 43.07118,
        "rating": 4.6,
        "excerpt": null,
        "detail_description": "La Bottega Dei Sapori is a charming eatery located on Piazza del Comune, 34. The cozy venue offers a delightful selection of porchetta, meats, cheeses, and panini at great prices. The owner takes pride in presenting authentic dishes sourced from the family farm. Guests can savor exquisite flatbread sandwiches featuring pecorino cheese and pancetta while enjoying fantastic local wines.",
        "imageKeys": [
            "L96wURvAHjHyBFeJdNHp3xJEAF9GIEbs",
            "YhOjCWVFA6ZLhBUuvrs9DknTr4JunPhV",
            "dgQLnyvbxK02o4Iaj4LF7xvi32HrX5yR",
            "aGMVUnchjIcxwcGnXkZv9aPh2zQUEdqs"
        ],
        "ratingCount": 231,
        "openingPeriods": [
            {
                "open": {
                    "day": 0,
                    "time": "1000"
                },
                "close": {
                    "day": 0,
                    "time": "1930"
                }
            },
            {
                "open": {
                    "day": 1,
                    "time": "1000"
                },
                "close": {
                    "day": 1,
                    "time": "1900"
                }
            },
            {
                "open": {
                    "day": 3,
                    "time": "1000"
                },
                "close": {
                    "day": 3,
                    "time": "1900"
                }
            },
            {
                "open": {
                    "day": 4,
                    "time": "1000"
                },
                "close": {
                    "day": 4,
                    "time": "1900"
                }
            },
            {
                "open": {
                    "day": 5,
                    "time": "1000"
                },
                "close": {
                    "day": 5,
                    "time": "1930"
                }
            },
            {
                "open": {
                    "day": 6,
                    "time": "1000"
                },
                "close": {
                    "day": 6,
                    "time": "1930"
                }
            }
        ],
        "name": "La Bottega Dei Sapori",
        "permanentlyClosed": false,
        "priceLevel": null,
        "phone": "+39 075 812294",
        "address": "Piazza del Comune, 34, 06081 Assisi PG, Italy",
        "types": [
            "Grocery store"
        ],
        "ratingDistribution": {
            "Google": {
                "1": 14,
                "2": 1,
                "3": 7,
                "4": 9,
                "5": 200
            }
        }
    },
    {
        "placeId": "ChIJAyKo9DadLhMRh2hTvGEHMas",
        "website": "http://www.lalocandadelcardinale.com/",
        "index": 18,
        "utcOffset": 120,
        "longitude": 12.614472,
        "latitude": 43.07013,
        "rating": 4.6,
        "excerpt": "Refined Italian dishes in a brick vault with glass floors, above remains of an ancient Roman villa.",
        "detail_description": "Nestled in the heart of Assisi, La Locanda del Cardinale offers a dining experience that beautifully marries history with modern culinary artistry. Set within an ancient Roman villa, this upscale restaurant features stunning brick vaults and glass floors that allow diners to gaze down at the remnants of a bygone era, including part of the street leading to the Temple of Minerva. The ambiance is both elegant and inviting, enhanced by contemporary decor and sparkling chandeliers that complement the historical setting.",
        "imageKeys": [
            "tuYHD2ksxoGUAD8MNmHW8Fk1raTkT2H3",
            "aPRuYmATRjDgBQOal61LNrhfN61Rnbui"
        ],
        "ratingCount": 362,
        "openingPeriods": [
            {
                "open": {
                    "day": 0,
                    "time": "1230"
                },
                "close": {
                    "day": 0,
                    "time": "1400"
                }
            },
            {
                "open": {
                    "day": 0,
                    "time": "1930"
                },
                "close": {
                    "day": 0,
                    "time": "2200"
                }
            },
            {
                "open": {
                    "day": 1,
                    "time": "1930"
                },
                "close": {
                    "day": 1,
                    "time": "2200"
                }
            },
            {
                "open": {
                    "day": 3,
                    "time": "1930"
                },
                "close": {
                    "day": 3,
                    "time": "2200"
                }
            },
            {
                "open": {
                    "day": 4,
                    "time": "1230"
                },
                "close": {
                    "day": 4,
                    "time": "1400"
                }
            },
            {
                "open": {
                    "day": 4,
                    "time": "1930"
                },
                "close": {
                    "day": 4,
                    "time": "2200"
                }
            },
            {
                "open": {
                    "day": 5,
                    "time": "1230"
                },
                "close": {
                    "day": 5,
                    "time": "1400"
                }
            },
            {
                "open": {
                    "day": 5,
                    "time": "1930"
                },
                "close": {
                    "day": 5,
                    "time": "2200"
                }
            },
            {
                "open": {
                    "day": 6,
                    "time": "1230"
                },
                "close": {
                    "day": 6,
                    "time": "1400"
                }
            },
            {
                "open": {
                    "day": 6,
                    "time": "1930"
                },
                "close": {
                    "day": 6,
                    "time": "2230"
                }
            }
        ],
        "name": "La Locanda del Cardinale",
        "permanentlyClosed": false,
        "priceLevel": 3,
        "phone": "+39 075 815245",
        "address": "Piazza del Vescovado, 8, 06081 Assisi PG, Italy",
        "types": [
            "Restaurant"
        ],
        "ratingDistribution": {
            "Google": {
                "1": 15,
                "2": 8,
                "3": 14,
                "4": 50,
                "5": 275
            }
        }
    },
    {
        "placeId": "ChIJM4AqaTadLhMRsDsycyC896I",
        "website": null,
        "index": 19,
        "utcOffset": 120,
        "longitude": 12.614709,
        "latitude": 43.071186,
        "rating": null,
        "excerpt": null,
        "detail_description": "Piazza del Comune, located in Assisi, is a bustling square surrounded by significant historical landmarks such as the Temple of Minerva and the impressive Torre del Popolo. As the main square of the town, it exudes a vibrant atmosphere and serves as a central hub for various activities.",
        "imageKeys": [
            "mq5ZjImbK5PDDPPIc0y6DG4YSjIuKxhp",
            "Tp4X7DcfqI9Gru82ccxyeJ7hBZik2X38",
            "ziThYvF4ZmrgU4qwlOMYghzn3XhFe4nY",
            "QPu04rOpIv2X5Ru8A9SB4rgfcC33brv4",
            "NnBD9IoN0EX1X6rRdQRGROtaxA2YiaTC"
        ],
        "ratingCount": null,
        "openingPeriods": null,
        "name": "Piazza del Comune",
        "permanentlyClosed": false,
        "priceLevel": null,
        "phone": null,
        "address": "06081 Assisi PG, Italy",
        "types": [
            "Sights & Landmarks",
            "Points of Interest & Landmarks"
        ],
        "ratingDistribution": {
            "Google": {
                "1": 0,
                "2": 0,
                "3": 0,
                "4": 0,
                "5": 0
            }
        }
    },
    {
        "placeId": "ChIJXxWt8DWdLhMRn7GX-I6_wBo",
        "website": null,
        "index": 20,
        "utcOffset": 120,
        "longitude": 12.609783,
        "latitude": 43.072721,
        "rating": 4.8,
        "excerpt": null,
        "detail_description": "The Oratorio dei Pellegrini is a small triangular church that originally served as a hostel for pilgrims traveling to Rome to pay homage to the remains of Francis. The chapel features beautiful art and frescoes, including works by Matteo da Gualdo from the 15th century. It is tucked away behind a glass door on via San Francesco, offering a quiet space to admire its magnificent paintings and frescoes without disturbing praying pilgrims.",
        "imageKeys": [
            "BLNYyM5fN0DyW18fTP18IYpjJbIwRBeA",
            "psTH6JvwOABnK0PXHfgLHGR7ikWUrCQZ",
            "jEbVHfVk7R6xdViyltjibNxIuXSpXNNO",
            "I1xbmUFvzar3heidsVvJ4jjcx5KzFdss"
        ],
        "ratingCount": 15,
        "openingPeriods": [
            {
                "open": {
                    "day": 1,
                    "time": "0900"
                },
                "close": {
                    "day": 1,
                    "time": "1200"
                }
            },
            {
                "open": {
                    "day": 1,
                    "time": "1600"
                },
                "close": {
                    "day": 1,
                    "time": "1800"
                }
            },
            {
                "open": {
                    "day": 2,
                    "time": "0900"
                },
                "close": {
                    "day": 2,
                    "time": "1200"
                }
            },
            {
                "open": {
                    "day": 2,
                    "time": "1600"
                },
                "close": {
                    "day": 2,
                    "time": "1800"
                }
            },
            {
                "open": {
                    "day": 3,
                    "time": "0900"
                },
                "close": {
                    "day": 3,
                    "time": "1200"
                }
            },
            {
                "open": {
                    "day": 3,
                    "time": "1600"
                },
                "close": {
                    "day": 3,
                    "time": "1800"
                }
            },
            {
                "open": {
                    "day": 4,
                    "time": "0900"
                },
                "close": {
                    "day": 4,
                    "time": "1200"
                }
            },
            {
                "open": {
                    "day": 4,
                    "time": "1600"
                },
                "close": {
                    "day": 4,
                    "time": "1800"
                }
            },
            {
                "open": {
                    "day": 5,
                    "time": "0900"
                },
                "close": {
                    "day": 5,
                    "time": "1200"
                }
            },
            {
                "open": {
                    "day": 5,
                    "time": "1600"
                },
                "close": {
                    "day": 5,
                    "time": "1800"
                }
            },
            {
                "open": {
                    "day": 6,
                    "time": "1600"
                },
                "close": {
                    "day": 6,
                    "time": "1800"
                }
            }
        ],
        "name": "Oratorio dei pellegrini",
        "permanentlyClosed": false,
        "priceLevel": null,
        "phone": null,
        "address": "Via San Francesco, 13, 06081 Assisi PG, Italy",
        "types": [
            "Catholic church",
            "Sights & Landmarks",
            "Sacred & Religious Sites",
            "Historic Sites"
        ],
        "ratingDistribution": {
            "Google": {
                "1": 0,
                "2": 0,
                "3": 1,
                "4": 1,
                "5": 13
            }
        }
    }
]