[
    {
        "placeId": "ChIJyxIHyt2VuEwR8XlC8k4i1zw",
        "website": "http://portesaintequebec.ca/",
        "index": 1,
        "utcOffset": -240,
        "longitude": -71.206056,
        "latitude": 46.813777,
        "rating": 4.7,
        "excerpt": "Dating to 1647, this opulent church has been rebuilt a few times & features a historic crypt.",
        "detail_description": "Notre-Dame de Québec Basilica-Cathedral, dating back to 1647, has undergone several reconstructions and boasts a historic crypt. The cathedral's rich history is reflected in its opulent interior adorned with impressive works of art, including an Episcopal throne canopy, stained glass, paintings, sculptures, and a sanctuary lamp from Louis XIV. The site also houses the tombs of governors of New France and many bishops of Quebec City.",
        "imageKeys": [
            "HNXaiteDSv1Q7RW2KxGCtmyJf8lTv0hG",
            "iIPUAPnVP0PL9HPz6AhKezTBdfqkfXLk",
            "3g7M4HR2iWW9bbLC6vxtuVpeTrQDXhqy",
            "NXqaBY46tT1rsAPquOs7U8w6okVwHXdi",
            "XPBMWXtHQYnqSIucvSwW2nIUijmtofm4"
        ],
        "ratingCount": 4046,
        "openingPeriods": [
            {
                "open": {
                    "day": 0,
                    "time": "0830"
                },
                "close": {
                    "day": 0,
                    "time": "1700"
                }
            },
            {
                "open": {
                    "day": 1,
                    "time": "0730"
                },
                "close": {
                    "day": 1,
                    "time": "1600"
                }
            },
            {
                "open": {
                    "day": 2,
                    "time": "0730"
                },
                "close": {
                    "day": 2,
                    "time": "1600"
                }
            },
            {
                "open": {
                    "day": 3,
                    "time": "0730"
                },
                "close": {
                    "day": 3,
                    "time": "1600"
                }
            },
            {
                "open": {
                    "day": 4,
                    "time": "0730"
                },
                "close": {
                    "day": 4,
                    "time": "1600"
                }
            },
            {
                "open": {
                    "day": 5,
                    "time": "0730"
                },
                "close": {
                    "day": 5,
                    "time": "1600"
                }
            },
            {
                "open": {
                    "day": 6,
                    "time": "0730"
                },
                "close": {
                    "day": 6,
                    "time": "1700"
                }
            }
        ],
        "name": "Notre-Dame de Québec Basilica-Cathedral",
        "permanentlyClosed": false,
        "priceLevel": null,
        "phone": "+1 418-692-2533",
        "address": "16 Rue De Buade, Québec City, Quebec G1R 4A1, Canada",
        "types": [
            "Catholic cathedral",
            "Sights & Landmarks",
            "Basilica",
            "Catholic church",
            "Place of worship",
            "Sacred & Religious Sites",
            "Historic Sites"
        ],
        "ratingDistribution": {
            "Google": {
                "1": 20,
                "2": 24,
                "3": 177,
                "4": 791,
                "5": 3060
            }
        }
    },
    {
        "placeId": "ChIJn3Ir_NSVuEwR6Vri1JjUvsI",
        "website": "https://www.plainesdabraham.ca/",
        "index": 2,
        "utcOffset": -240,
        "longitude": -71.220291,
        "latitude": 46.800408,
        "rating": 4.7,
        "excerpt": "Set in a historic park, this battle site in the Seven Years' War features gardens & an ice rink.",
        "detail_description": "The Plains of Abraham is a historic park in Quebec, Canada, known for its pivotal role in the Seven Years' War. This urban park was the site of the famous Battle of Quebec in 1759, where British forces defeated the French. The park features gardens, an ice rink, and Martello Towers with family-friendly activities. Visitors can explore the Museum of the Plains of Abraham to learn about Canada's history through multimedia displays.",
        "imageKeys": [
            "J7Sr2lDpk2QssUsGte2PFVQOv1V74ChN",
            "ynh1CUqQihMmF8WT2SUordwwLgjQFsXD",
            "joRYyksec80cZuWgJbVPRjHtKaU9SWRv",
            "MJSuvOLDYY6tklJZSPnhSCxKl1EOA9Tm",
            "xergMlDU6VjKHErAtj2LXeNI9d4oC7SV"
        ],
        "ratingCount": 8347,
        "openingPeriods": [
            {
                "open": {
                    "day": 0,
                    "time": "0000"
                }
            },
            {
                "open": {
                    "day": 1,
                    "time": "0000"
                }
            },
            {
                "open": {
                    "day": 2,
                    "time": "0000"
                }
            },
            {
                "open": {
                    "day": 3,
                    "time": "0000"
                }
            },
            {
                "open": {
                    "day": 4,
                    "time": "0000"
                }
            },
            {
                "open": {
                    "day": 5,
                    "time": "0000"
                }
            },
            {
                "open": {
                    "day": 6,
                    "time": "0000"
                }
            }
        ],
        "name": "Plains of Abraham",
        "permanentlyClosed": false,
        "priceLevel": null,
        "phone": "+1 418-649-6157",
        "address": "835 Wilfrid-Laurier Ave, Québec City, Quebec G1R 2L3, Canada",
        "types": [
            "Park",
            "Historical landmark",
            "Museum"
        ],
        "ratingDistribution": {
            "Google": {
                "1": 35,
                "2": 32,
                "3": 238,
                "4": 1526,
                "5": 6515
            }
        }
    },
    {
        "placeId": "ChIJVQoHldyVuEwRaz-G5nNKUhE",
        "website": "http://www.quartierpetitchamplain.com/",
        "index": 3,
        "utcOffset": -240,
        "longitude": -71.20355,
        "latitude": 46.811763,
        "rating": 4.7,
        "excerpt": "Cooperative-owned shopping quarter with independent boutiques, galleries, restaurants & a theatre.",
        "detail_description": "Nestled in the old ports district, Quartier Petit Champlain is a cooperative-owned shopping quarter featuring independent boutiques, galleries, restaurants, and a theater. This historic area is renowned as the oldest commercial district in North America and has been a hub for craftsmen, merchants, and artists for generations. The pedestrian-only streets are popular year-round, offering a charming atmosphere with snow-capped structures during the ski season and authentic French restaurants serving local delicacies and ice wine.",
        "imageKeys": [
            "06nDVqZzpuc9iNvSfIzmyKrUOOHAMgj6",
            "SqiJHn6AjFqEmDy8vvu6Y94hKUggP2dA",
            "O34BB7akG4dy2wCyAVsMjd3ttXPqvQKo",
            "5ArPXWwhwofbFRnLygsZanohIjz8p0Jl",
            "YbIiNMrTCvDvZFmvlkxYNwGr8apoQzO4"
        ],
        "ratingCount": 6897,
        "openingPeriods": null,
        "name": "Quartier Petit Champlain",
        "permanentlyClosed": false,
        "priceLevel": null,
        "phone": "+1 418-692-2613",
        "address": "61 Rue du Petit Champlain, Québec City, Quebec G1K 4H5, Canada",
        "types": [
            "Shopping mall"
        ],
        "ratingDistribution": {
            "Google": {
                "1": 29,
                "2": 30,
                "3": 185,
                "4": 1269,
                "5": 5417
            }
        }
    },
    {
        "placeId": "ChIJk4jbBYqWuEwRAzro8GMtxY8",
        "website": "http://www.ville.quebec.qc.ca/index.aspx",
        "index": 4,
        "utcOffset": -240,
        "longitude": -71.20746,
        "latitude": 46.813082,
        "rating": null,
        "excerpt": "Québec City sits on the Saint Lawrence River in Canada's mostly French-speaking Québec province. Dating to 1608, it has a fortified colonial core, Vieux-Québec and Place Royale, with stone buildings and narrow streets. This area is the site of the towering Château Frontenac Hotel and imposing Citadelle of Québec. The Petit Champlain district’s cobblestone streets are lined with bistros and boutiques.",
        "detail_description": "Québec City, located in Canada's Québec province, is a historic gem dating back to 1608. Its Vieux-Québec and Place Royale areas boast charming stone buildings and narrow streets, including the iconic Château Frontenac Hotel and Citadelle of Québec. The Petit Champlain district offers cobblestone streets lined with quaint bistros and boutiques.",
        "imageKeys": [
            "JbFpyqj2rLEheEowfxm5lpkIfRcYbDXa",
            "lFgKTcdrJxXAhMnhCjZy1tnGEvw08ISx",
            "l6rTX9BDucp8SEsOACwyJoPEZe1OVOQJ",
            "cpQWPKvvEgGnT9X06QBxIM4ZbqE9i1G4",
            "fN8Z8aIfYaD7dXYx4gtfWvksVHUs7De3"
        ],
        "ratingCount": null,
        "openingPeriods": null,
        "name": "Québec City",
        "permanentlyClosed": false,
        "priceLevel": null,
        "phone": null,
        "address": "Quebec, Canada",
        "types": [
            "Visitor Centers"
        ],
        "ratingDistribution": {
            "Google": {
                "1": 0,
                "2": 0,
                "3": 0,
                "4": 0,
                "5": 0
            }
        }
    },
    {
        "placeId": "ChIJe-AHHN2VuEwRV_Nq2B_lBSE",
        "website": "https://www.placeroyale.ca/en/",
        "index": 5,
        "utcOffset": -240,
        "longitude": -71.202752,
        "latitude": 46.813106,
        "rating": 4.7,
        "excerpt": "Picturesque cobblestoned square flanked by cafes, shops & a 17th-century stone church.",
        "detail_description": "Place Royale in Quebec City, Canada is a charming cobblestoned square surrounded by cafes, shops, and a 17th-century stone church. This historic landmark dates back to the early 17th century and is an integral part of Old Quebec. It was the site where Samuel de Champlain founded the city in 1608. The area is filled with restaurants, coffee shops, and unique places to visit that are rich in history and character.",
        "imageKeys": [
            "oftmdeCii6cE6hQXbBpZ7uhSuPty2uev",
            "CsBVVhVZkXqtruyXCJzueneSq35Phjks",
            "xJaCyRmBPbPw0XevnGtOPgy0yNZ7Zvbk",
            "pOdIcWfW6h4WspOU5YTT0MVehq4DJ3AH",
            "xLif6xOBaa8QwKdYW1U6nHP1icujWEEt"
        ],
        "ratingCount": 2166,
        "openingPeriods": [
            {
                "open": {
                    "day": 0,
                    "time": "0000"
                }
            },
            {
                "open": {
                    "day": 1,
                    "time": "0000"
                }
            },
            {
                "open": {
                    "day": 2,
                    "time": "0000"
                }
            },
            {
                "open": {
                    "day": 3,
                    "time": "0000"
                }
            },
            {
                "open": {
                    "day": 4,
                    "time": "0000"
                }
            },
            {
                "open": {
                    "day": 5,
                    "time": "0000"
                }
            },
            {
                "open": {
                    "day": 6,
                    "time": "0000"
                }
            }
        ],
        "name": "Place Royale",
        "permanentlyClosed": false,
        "priceLevel": null,
        "phone": "+1 418-643-2581",
        "address": "2-4 Rue des Pains Bénits, Ville de Québec, QC G1K Rue des Pains Bénits, Québec City, Quebec G1K 4E9, Canada",
        "types": [
            "Historical landmark",
            "Historic Walking Areas",
            "Neighborhoods",
            "Points of Interest & Landmarks"
        ],
        "ratingDistribution": {
            "Google": {
                "1": 12,
                "2": 10,
                "3": 69,
                "4": 386,
                "5": 1714
            }
        }
    },
    {
        "placeId": "ChIJqwAQnqK-uEwRIxnWIPF1QtU",
        "website": "https://www.sepaq.com/destinations/parc-chute-montmorency/",
        "index": 6,
        "utcOffset": -240,
        "longitude": -71.147787,
        "latitude": 46.887504,
        "rating": 4.7,
        "excerpt": "Towering waterfall with scenic views from trails, steps, a suspension bridge & a tram.",
        "detail_description": "Montmorency Falls, located just a short distance from Quebec City, is an awe-inspiring natural attraction standing at 83 meters tall, even higher than Niagara Falls. Visitors can enjoy various activities year-round, such as hiking in the summer and ice climbing in the winter. The falls are easily accessible by car or bike and offer stunning views from different vantage points including trails, a suspension bridge, and a tram.",
        "imageKeys": [
            "TFbfime7LdFRs26k18uppd5wpHeT1B13",
            "CLVyhVi4YguphBtC27s4Wasx7OJoIVDf",
            "OZALVm6gfNqLNM449AFuovfYpRwW3kJ9",
            "9tsNL9FaKMSLsaWtM1yhIwSCtQXx0E5A",
            "GnOecIzA0I4Bx7bdoV2H166aOhrRESAJ"
        ],
        "ratingCount": 32747,
        "openingPeriods": [
            {
                "open": {
                    "day": 0,
                    "time": "0900"
                },
                "close": {
                    "day": 0,
                    "time": "1800"
                }
            },
            {
                "open": {
                    "day": 1,
                    "time": "0900"
                },
                "close": {
                    "day": 1,
                    "time": "1800"
                }
            },
            {
                "open": {
                    "day": 2,
                    "time": "0900"
                },
                "close": {
                    "day": 2,
                    "time": "1800"
                }
            },
            {
                "open": {
                    "day": 3,
                    "time": "0900"
                },
                "close": {
                    "day": 3,
                    "time": "1800"
                }
            },
            {
                "open": {
                    "day": 4,
                    "time": "0900"
                },
                "close": {
                    "day": 4,
                    "time": "1800"
                }
            },
            {
                "open": {
                    "day": 5,
                    "time": "0900"
                },
                "close": {
                    "day": 5,
                    "time": "1800"
                }
            },
            {
                "open": {
                    "day": 6,
                    "time": "0900"
                },
                "close": {
                    "day": 6,
                    "time": "1800"
                }
            }
        ],
        "name": "Montmorency Falls",
        "permanentlyClosed": false,
        "priceLevel": null,
        "phone": "+1 418-663-3330",
        "address": "Québec City, Quebec G1C 2H1, Canada",
        "types": [
            "Nature & Parks",
            "Parks",
            "State Parks",
            "Waterfalls"
        ],
        "ratingDistribution": {
            "Google": {
                "1": 263,
                "2": 303,
                "3": 1334,
                "4": 6723,
                "5": 24405
            }
        }
    },
    {
        "placeId": "ChIJO_wtXNqVuEwRBoNhbzRrcZg",
        "website": "http://www.lacitadelle.qc.ca/",
        "index": 7,
        "utcOffset": -240,
        "longitude": -71.206899,
        "latitude": 46.8078,
        "rating": 4.6,
        "excerpt": "Complex featuring a long-standing active fort, plus a museum & changing of the guard ceremonies.",
        "detail_description": "The Citadelle of Québec is a historic complex that includes an active fort, a museum, and the traditional Changing of the Guard ceremony. However, during certain times of the year, this ceremony is replaced by a musical performance by the Royal 22nd Regiment Band. The citadel has been an important part of Quebec's history since it was rebuilt by the British in the 19th century.",
        "imageKeys": [
            "tqAOdabt4X1qYd8EGQFvjhRGqI5WRilz",
            "Ox6NLxDmfi8JX10d6NbKqON470mTZ3wn",
            "P6vL7pDGIZPyzX4MeES8kzQqBRN3sutW",
            "4peCZ4n0PoWYeyqdjSooU0XFfMJ5JhGC",
            "dUBm0hWqJ91L3HInOkf4FxYZsnvkYdJY"
        ],
        "ratingCount": 8627,
        "openingPeriods": [
            {
                "open": {
                    "day": 0,
                    "time": "0900"
                },
                "close": {
                    "day": 0,
                    "time": "1730"
                }
            },
            {
                "open": {
                    "day": 1,
                    "time": "0900"
                },
                "close": {
                    "day": 1,
                    "time": "1730"
                }
            },
            {
                "open": {
                    "day": 2,
                    "time": "0900"
                },
                "close": {
                    "day": 2,
                    "time": "1730"
                }
            },
            {
                "open": {
                    "day": 3,
                    "time": "0900"
                },
                "close": {
                    "day": 3,
                    "time": "1730"
                }
            },
            {
                "open": {
                    "day": 4,
                    "time": "0900"
                },
                "close": {
                    "day": 4,
                    "time": "1730"
                }
            },
            {
                "open": {
                    "day": 5,
                    "time": "0900"
                },
                "close": {
                    "day": 5,
                    "time": "1730"
                }
            },
            {
                "open": {
                    "day": 6,
                    "time": "0900"
                },
                "close": {
                    "day": 6,
                    "time": "1730"
                }
            }
        ],
        "name": "The Citadelle of Québec",
        "permanentlyClosed": false,
        "priceLevel": null,
        "phone": "+1 418-694-2800",
        "address": "1 Côte de la Citadelle, Québec City, Quebec G1R 3R2, Canada",
        "types": [
            "Fortress",
            "Museums",
            "Historical landmark",
            "History Museums",
            "Military Museums",
            "Specialty Museums"
        ],
        "ratingDistribution": {
            "Google": {
                "1": 51,
                "2": 84,
                "3": 409,
                "4": 1875,
                "5": 6249
            }
        }
    },
    {
        "placeId": "ChIJ-WwxG3iWuEwRAJcGS1DuX9g",
        "website": "http://www.observatoire-capitale.com/",
        "index": 8,
        "utcOffset": -240,
        "longitude": -71.217834,
        "latitude": 46.80797,
        "rating": 4.5,
        "excerpt": "Viewing space on the 31st floor of the Marie-Guyart Building, the city's tallest skyscraper at 132m.",
        "detail_description": "The Observatoire de la Capitale, located on the 31st floor of the Marie-Guyart Building, offers a stunning 360-degree view of Quebec City. As the city's tallest skyscraper at 132m, it provides an unparalleled vantage point to admire historic landmarks such as Old Quebec and Cap Diamant, as well as scenic features like the St. Lawrence River and the Louise Basin marina.",
        "imageKeys": [
            "7Z1both9rw2q5koqHqQezGtPl6wnCUwB",
            "WbPenNVF0dOrb92gmwKTw4DD97OhHS9T",
            "7Q7Yy3EJzouPgasP31VhU1La8DhIs3Z8",
            "LJ1YU7YdhuLUXN17ff1DbyC9h4MP4KaI",
            "dMQLmtcMyXD9BHMatsISJRbekETjkW20"
        ],
        "ratingCount": 1264,
        "openingPeriods": [
            {
                "open": {
                    "day": 0,
                    "time": "1000"
                },
                "close": {
                    "day": 0,
                    "time": "1700"
                }
            },
            {
                "open": {
                    "day": 1,
                    "time": "1000"
                },
                "close": {
                    "day": 1,
                    "time": "1700"
                }
            },
            {
                "open": {
                    "day": 2,
                    "time": "1000"
                },
                "close": {
                    "day": 2,
                    "time": "1700"
                }
            },
            {
                "open": {
                    "day": 3,
                    "time": "1000"
                },
                "close": {
                    "day": 3,
                    "time": "1700"
                }
            },
            {
                "open": {
                    "day": 4,
                    "time": "1000"
                },
                "close": {
                    "day": 4,
                    "time": "1700"
                }
            },
            {
                "open": {
                    "day": 5,
                    "time": "1000"
                },
                "close": {
                    "day": 5,
                    "time": "1700"
                }
            },
            {
                "open": {
                    "day": 6,
                    "time": "1000"
                },
                "close": {
                    "day": 6,
                    "time": "1700"
                }
            }
        ],
        "name": "Observatoire de la Capitale",
        "permanentlyClosed": false,
        "priceLevel": null,
        "phone": "+1 418-644-9841",
        "address": "1037 Rue de la Chevrotière, Québec City, Quebec G1R 5E9, Canada",
        "types": [
            "Sights & Landmarks",
            "Observation Decks & Towers"
        ],
        "ratingDistribution": {
            "Google": {
                "1": 18,
                "2": 26,
                "3": 115,
                "4": 319,
                "5": 800
            }
        }
    },
    {
        "placeId": "ChIJKRaHYtyVuEwRkAOg1c9lDVY",
        "website": "https://www.pc.gc.ca/saintlouis?utm_source=gmb&utm_medium=dufferin",
        "index": 9,
        "utcOffset": -240,
        "longitude": -71.204304,
        "latitude": 46.811445,
        "rating": 4.8,
        "excerpt": "Built in 1859, this long, popular terrace overlooking the river also offers scenic city views.",
        "detail_description": "Dufferin Terrace, also known as Terrasse Dufferin, is a historic wooden boardwalk built in 1859 that offers stunning views of the Saint Lawrence River, Chateau Frontenac, and the Citadel of Quebec. It is a popular spot for both locals and tourists to enjoy leisurely strolls while taking in panoramic city views. In the winter, visitors can experience the famous Terrasse Dufferin Slides toboggan run during the Quebec Winter Carnival.",
        "imageKeys": [
            "1ARs83siPsIbbKgSqbp4ZxthxRZ3vgE2",
            "TLi0b4JsIDMkjsVaRkC7c0nGMJBmlAH4",
            "erDqOJgzq0J7dxDafQfUq28QOm89TBK0",
            "IfoxSlzUaCjmD6X6xnlLpSylWeJdGkS3",
            "HfqmZdGPzXWYfg4yoj8hmn5AApqXMfeN"
        ],
        "ratingCount": 2025,
        "openingPeriods": [
            {
                "open": {
                    "day": 0,
                    "time": "0000"
                }
            },
            {
                "open": {
                    "day": 1,
                    "time": "0000"
                }
            },
            {
                "open": {
                    "day": 2,
                    "time": "0000"
                }
            },
            {
                "open": {
                    "day": 3,
                    "time": "0000"
                }
            },
            {
                "open": {
                    "day": 4,
                    "time": "0000"
                }
            },
            {
                "open": {
                    "day": 5,
                    "time": "0000"
                }
            },
            {
                "open": {
                    "day": 6,
                    "time": "0000"
                }
            }
        ],
        "name": "Dufferin Terrace",
        "permanentlyClosed": false,
        "priceLevel": null,
        "phone": "(888) 773-8888",
        "address": "Rue des Carrières, Québec City, Quebec G1R 5J5, Canada",
        "types": [
            "Historical landmark"
        ],
        "ratingDistribution": {
            "Google": {
                "1": 8,
                "2": 4,
                "3": 38,
                "4": 323,
                "5": 1667
            }
        }
    },
    {
        "placeId": "ChIJb7O4NtiVuEwROoa3BZWSsLA",
        "website": "https://www.assnat.qc.ca/",
        "index": 10,
        "utcOffset": -240,
        "longitude": -71.214179,
        "latitude": 46.808706,
        "rating": 4.5,
        "excerpt": "This Second Empire-style building is home to Quebec's National Assembly & offers free guided tours.",
        "detail_description": "The Parliament Building, located in Quebec City's St. Jean Baptiste district, is a stunning Second Empire-style structure surrounded by beautiful gardens. Dating back to the late 19th century, it serves as an important center of politics and offers free guided tours of its well-preserved interior with impressive architecture. The grounds are adorned with numerous monuments and 26 bronze statues that pay homage to key figures in Quebec's political history.",
        "imageKeys": [
            "GEOMRUgPhKKBQDvNT3LB9oultJVmEm6v",
            "BSr0ypUBCSmjNXGkDrHdbKH8UhuIMXPK",
            "9MF1UKG2YlAfy6BIu1wsUV8nEAR7GFKT",
            "n0uOZqIRHJC3mTdX6j2SHzoKObj6FMUG",
            "YNudxMLIYVy9p813iJFYXMFWCZUPFxif"
        ],
        "ratingCount": 553,
        "openingPeriods": [
            {
                "open": {
                    "day": 1,
                    "time": "0830"
                },
                "close": {
                    "day": 1,
                    "time": "1630"
                }
            },
            {
                "open": {
                    "day": 2,
                    "time": "0830"
                },
                "close": {
                    "day": 2,
                    "time": "1630"
                }
            },
            {
                "open": {
                    "day": 3,
                    "time": "0830"
                },
                "close": {
                    "day": 3,
                    "time": "1630"
                }
            },
            {
                "open": {
                    "day": 4,
                    "time": "0830"
                },
                "close": {
                    "day": 4,
                    "time": "1630"
                }
            },
            {
                "open": {
                    "day": 5,
                    "time": "0830"
                },
                "close": {
                    "day": 5,
                    "time": "1630"
                }
            },
            {
                "open": {
                    "day": 6,
                    "time": "0930"
                },
                "close": {
                    "day": 6,
                    "time": "1630"
                }
            }
        ],
        "name": "Parliament Building",
        "permanentlyClosed": false,
        "priceLevel": null,
        "phone": "+1 418-643-7239",
        "address": "1045 Rue des Parlementaires, Québec City, Quebec G1A 1A3, Canada",
        "types": [
            "Government office",
            "Sights & Landmarks",
            "Assembly hall",
            "Government Buildings"
        ],
        "ratingDistribution": {
            "Google": {
                "1": 33,
                "2": 8,
                "3": 19,
                "4": 94,
                "5": 404
            }
        }
    },
    {
        "placeId": "ChIJn5duwH-WuEwRo6FhOQuuTIw",
        "website": "http://www.mnbaq.org/",
        "index": 11,
        "utcOffset": -240,
        "longitude": -71.224883,
        "latitude": 46.800852,
        "rating": 4.6,
        "excerpt": "Works by Quebecois artists including Alfred Pellan, plus paintings of Quebec & touring exhibitions.",
        "detail_description": "The Musée national des beaux-arts du Québec, located on the vibrant Grand Allee, is a neoclassical museum with a modern wing designed by renowned architects Rem Koolhaas and Shohei Shigematsu. The Lassonde Pavilion, added in 2016, showcases a remarkable collection of 22,000 traditional and contemporary Quebec art pieces.",
        "imageKeys": [
            "z7I3BwB3tEwQJcWeRCIDciSA34QLcT5B",
            "RjybJrXJJ6CYydw2s3hfymMZNAhWl4s4",
            "aJIg39ORWfVMJAibjaA6OS1Fi1ytWy70",
            "sP7C6JKiYizV9qjx7rlmOstqFBDaDUHN",
            "cRJVPMHUQ6X7y2DHTcnogiZ3Ir5aoYdR"
        ],
        "ratingCount": 4040,
        "openingPeriods": [
            {
                "open": {
                    "day": 0,
                    "time": "1000"
                },
                "close": {
                    "day": 0,
                    "time": "1700"
                }
            },
            {
                "open": {
                    "day": 1,
                    "time": "1000"
                },
                "close": {
                    "day": 1,
                    "time": "1700"
                }
            },
            {
                "open": {
                    "day": 2,
                    "time": "1000"
                },
                "close": {
                    "day": 2,
                    "time": "1700"
                }
            },
            {
                "open": {
                    "day": 3,
                    "time": "1000"
                },
                "close": {
                    "day": 3,
                    "time": "2100"
                }
            },
            {
                "open": {
                    "day": 4,
                    "time": "1000"
                },
                "close": {
                    "day": 4,
                    "time": "1700"
                }
            },
            {
                "open": {
                    "day": 5,
                    "time": "1000"
                },
                "close": {
                    "day": 5,
                    "time": "1700"
                }
            },
            {
                "open": {
                    "day": 6,
                    "time": "1000"
                },
                "close": {
                    "day": 6,
                    "time": "1700"
                }
            }
        ],
        "name": "Musée national des beaux-arts du Québec",
        "permanentlyClosed": false,
        "priceLevel": null,
        "phone": "+1 418-643-2150",
        "address": "179 Grande Allée O, Québec City, Quebec G1R 2H1, Canada",
        "types": [
            "Art museum",
            "Museums",
            "Architectural Buildings",
            "History Museums"
        ],
        "ratingDistribution": {
            "Google": {
                "1": 77,
                "2": 45,
                "3": 195,
                "4": 808,
                "5": 2943
            }
        }
    },
    {
        "placeId": "ChIJK7_LO9aVuEwRUPWWmG87KwQ",
        "website": null,
        "index": 12,
        "utcOffset": -240,
        "longitude": -71.206493,
        "latitude": 46.812182,
        "rating": null,
        "excerpt": null,
        "detail_description": "Old Quebec, the historic heart of Quebec City, encompasses both the Upper Town (Haute-Ville) and Lower Town (Basse-Ville) along the St Lawrence River. Enclosed by 2.85 miles of fortifications, it is adorned with historic landmarks and presided over by Chateau Frontenac, a picturesque castle that functions as the city's premier hotel.",
        "imageKeys": [
            "NYyuCLfLdP5ACA9qLp0FrEzjc5MU1GYK",
            "mklwSjq4IvyMOyorcvbeD8yvMjxumIGR",
            "5RcYj2F8GWN436ijQb7bKHPdDTGNJqoF",
            "i2124CURgEOcklR9xvO8o5rvv4BSXaUm",
            "tgm872GSbSb6qREimvzDD6QrRWtUeYTZ"
        ],
        "ratingCount": null,
        "openingPeriods": null,
        "name": "Old Quebec",
        "permanentlyClosed": false,
        "priceLevel": null,
        "phone": null,
        "address": "Québec City, QC, Canada",
        "types": [
            "Historic Walking Areas",
            "Neighborhoods"
        ],
        "ratingDistribution": {
            "Google": {
                "1": 0,
                "2": 0,
                "3": 0,
                "4": 0,
                "5": 0
            }
        }
    },
    {
        "placeId": "ChIJ5VH7596VuEwRY9ackQDg4yU",
        "website": "http://www.morrin.org/",
        "index": 13,
        "utcOffset": -240,
        "longitude": -71.21045,
        "latitude": 46.812737,
        "rating": 4.6,
        "excerpt": "Former city prison, built in 1808, hosting English-language culture & arts programs & tours.",
        "detail_description": "The Morrin Centre, located in Quebec City, is a historic landmark that was originally built as the city's first prison in 1808. Today, it houses the Literary and Historical Society of Quebec and features a vast English-language library with over 20,000 books, archives, manuscripts, films, artifacts, and decorative items related to English families of Quebec City.",
        "imageKeys": [
            "Vtu1aPbkfrqkUpxzTGN9nlb23sfHmgym",
            "nsqjF6z6rIM1YXOoup47Aecnp20CPzVf",
            "hxACrKQGcdEzY1LuTQh2OoJtVclv24pk",
            "BlER029zxAA9HdOARNsCicyAQ522cGZP",
            "zTzsrSFVbaByzskyvaYnpdbWdhucIA9i"
        ],
        "ratingCount": 602,
        "openingPeriods": [
            {
                "open": {
                    "day": 0,
                    "time": "1000"
                },
                "close": {
                    "day": 0,
                    "time": "1600"
                }
            },
            {
                "open": {
                    "day": 1,
                    "time": "1000"
                },
                "close": {
                    "day": 1,
                    "time": "1600"
                }
            },
            {
                "open": {
                    "day": 2,
                    "time": "0900"
                },
                "close": {
                    "day": 2,
                    "time": "1700"
                }
            },
            {
                "open": {
                    "day": 3,
                    "time": "1000"
                },
                "close": {
                    "day": 3,
                    "time": "1600"
                }
            },
            {
                "open": {
                    "day": 4,
                    "time": "1000"
                },
                "close": {
                    "day": 4,
                    "time": "1600"
                }
            },
            {
                "open": {
                    "day": 5,
                    "time": "1000"
                },
                "close": {
                    "day": 5,
                    "time": "1600"
                }
            },
            {
                "open": {
                    "day": 6,
                    "time": "1000"
                },
                "close": {
                    "day": 6,
                    "time": "1600"
                }
            }
        ],
        "name": "Morrin Centre",
        "permanentlyClosed": false,
        "priceLevel": null,
        "phone": "+1 418-694-9147",
        "address": "44 Chau. des Écossais, Québec City, Quebec G1R 4H3, Canada",
        "types": [
            "Cultural center",
            "Historical landmark",
            "Historical society",
            "Library",
            "Museum",
            "Non-profit organization",
            "Wedding venue"
        ],
        "ratingDistribution": {
            "Google": {
                "1": 6,
                "2": 7,
                "3": 23,
                "4": 127,
                "5": 442
            }
        }
    },
    {
        "placeId": "ChIJvebzldyVuEwRVwWTNpKOaEA",
        "website": null,
        "index": 14,
        "utcOffset": -240,
        "longitude": -71.203514,
        "latitude": 46.811379,
        "rating": 4.8,
        "excerpt": "Quaint, narrow pedestrian street lined with restaurants, cafes & boutiques in elegant buildings.",
        "detail_description": "Rue du Petit Champlain is a charming, narrow pedestrian street located at the base of Cape Diamond in Quebec City. It is the heart of a quaint neighborhood that pays homage to Samuel de Champlain, the founder of Quebec City. This historic area is known for its old-world charm, with cozy cafes, quaint shops, and elegant buildings lining the cobblestone street.",
        "imageKeys": [
            "9dPKLQYHzQwsPnwHGGHAeNjHFz9BWcwV",
            "QRRpDYZgUIaxKrkeDeSNE7uR6dJaItCu",
            "Jzla0x05YB9v8aAETF6X81gOhiGV9Y1i",
            "uRhRzz5G2lS4xAwq3zWbpJHdiC6CyVbq",
            "3cOsPsgV0V0lL02eHu0v6vEGvUGE2kUt"
        ],
        "ratingCount": 122,
        "openingPeriods": null,
        "name": "Rue du Petit Champlain",
        "permanentlyClosed": false,
        "priceLevel": null,
        "phone": null,
        "address": "Québec, QC, Canada",
        "types": [
            "Notable street"
        ],
        "ratingDistribution": {
            "Google": {
                "1": 0,
                "2": 0,
                "3": 3,
                "4": 14,
                "5": 111
            }
        }
    },
    {
        "placeId": "ChIJVybGQHeWuEwRFv5xTbnxsJM",
        "website": "http://faubourgsaintjean.com/",
        "index": 15,
        "utcOffset": -240,
        "longitude": -71.222544,
        "latitude": 46.809893,
        "rating": null,
        "excerpt": "Home of the city's congress centre and the Grand Théâtre de Québec, this buzzing downtown neighbourhood is dotted with colourful houses and historic buildings such as the Saint-Jean-Baptiste Church. Quirky book and record shops add a bohemian air around Rue Saint-Jean, which draws tourists to its cozy bistros, boutiques, cafes and cake shops. Several watering holes offer live music, and many cater to a gay clientele.",
        "detail_description": "Saint-Jean-Baptiste is a lively downtown neighborhood in Quebec City, known for its vibrant atmosphere and historic charm. The area is home to the city's congress center, the Grand Théâtre de Québec, and the iconic Saint-Jean-Baptiste Church. Visitors can explore colorful houses, quirky book and record shops along Rue Saint-Jean, as well as cozy bistros, boutiques, cafes, and cake shops.",
        "imageKeys": [
            "uSNUMLgFU46LJRxj5TFpgeGoupI6tNqf",
            "OXnNcFruNgII5gUpgZmYGE16ub5FCQMP",
            "HemnF6YKPFDpTrJ8c7kLx9lbPUih2aWu",
            "EBNQKgLXEKHqOK5DN8wMt90Ig6PhTx9P"
        ],
        "ratingCount": null,
        "openingPeriods": null,
        "name": "Saint-Jean-Baptiste",
        "permanentlyClosed": false,
        "priceLevel": null,
        "phone": null,
        "address": "Québec City, QC, Canada",
        "types": [],
        "ratingDistribution": {
            "Google": {
                "1": 0,
                "2": 0,
                "3": 0,
                "4": 0,
                "5": 0
            }
        }
    },
    {
        "placeId": "ChIJ-xJqVwCVuEwRX_uGLNoDJBI",
        "website": null,
        "index": 16,
        "utcOffset": -240,
        "longitude": -71.206638,
        "latitude": 46.815423,
        "rating": 5,
        "excerpt": null,
        "detail_description": "Nestled along the banks of the St. Lawrence River, the Old City of Quebec is a charming blend of history and culture that captivates every visitor. This UNESCO World Heritage Site boasts beautifully preserved stone buildings and winding streets that transport you back in time. As you stroll through this historic neighborhood, you'll encounter must-see attractions like the Citadel, Quartier Petit-Champlain—one of North America's oldest shopping streets—and the stunning Notre-Dame de Quebec Basilica-Cathedral.",
        "imageKeys": [
            "6EL7lH0OR3HHaIRQjXTyhD3BIuqcHhTX",
            "I9ZpHvcnUdC0qW6jvjykUI49ww7WXbO9"
        ],
        "ratingCount": 4,
        "openingPeriods": null,
        "name": "Old City of Quebec",
        "permanentlyClosed": false,
        "priceLevel": null,
        "phone": null,
        "address": "Rue Hébert, Québec City, Quebec G1R 4K7, Canada",
        "types": [
            "Historical landmark"
        ],
        "ratingDistribution": {
            "Google": {
                "1": 0,
                "2": 0,
                "3": 0,
                "4": 0,
                "5": 1
            }
        }
    },
    {
        "placeId": "ChIJJ9khTNyVuEwRzT2Bjflz-f4",
        "website": "http://www.museedufort.com/",
        "index": 17,
        "utcOffset": -240,
        "longitude": -71.205182,
        "latitude": 46.813095,
        "rating": 4.5,
        "excerpt": "An animated diorama show depicts the city's historic military battles at this quaint museum.",
        "detail_description": "The Fort Museum, also known as Musee du Fort, is a quaint museum in Quebec City that offers a 30-minute multimedia exhibition showcasing the city's historic military battles. Through visual demonstrations and sound and light effects, visitors can immerse themselves in key events such as the battle on the Plains of Abraham and Benedict Arnold's march to Quebec City. The museum provides an entertaining and educational experience for families, making it a must-visit to understand the city's history.",
        "imageKeys": [
            "7nQyOXXDVHOaeHb4WOhkucSZJ7GZZddr",
            "X2lpiOEG50X4jgyvPWed0RebX1DU4JDx",
            "hH5aambo1J3Flp149i5joV3VEIC0inds",
            "4PWZ9rt0Dgc5WnNyHATtTNsBSh0VU59a",
            "Euz4b1IlNsM2khD7vM7R8dXWs6sOixXc"
        ],
        "ratingCount": 184,
        "openingPeriods": null,
        "name": "The Fort Museum",
        "permanentlyClosed": false,
        "priceLevel": null,
        "phone": "+1 418-692-2175",
        "address": "10 Rue Sainte-Anne, Québec City, Quebec G1R 4S7, Canada",
        "types": [
            "Museum",
            "History museum",
            "War museum",
            "Military Museums",
            "Specialty Museums"
        ],
        "ratingDistribution": {
            "Google": {
                "1": 1,
                "2": 4,
                "3": 15,
                "4": 41,
                "5": 124
            }
        }
    },
    {
        "placeId": "ChIJM0qq4dyVuEwR8iYaing9zuU",
        "website": "https://www.notre-dame-de-quebec.org/notre-dame-des-victoires-church",
        "index": 18,
        "utcOffset": -240,
        "longitude": -71.202758,
        "latitude": 46.812961,
        "rating": 4.6,
        "excerpt": "Stone church dedicated to St. Genevieve, dating to 1688 & rebuilt in 1763 after the Siege of Quebec.",
        "detail_description": "Notre-Dame-des-Victoires Catholic Church is a historic stone church in Quebec City, dedicated to St. Genevieve and boasting a rich history dating back to 1688. The church was rebuilt twice after being destroyed during the Siege of Quebec in 1759 and features unique elements of French Romanesque architecture.",
        "imageKeys": [
            "EII5I5FRaAHpoAemfSH9UE4zjGNayTS1",
            "MJ4DUUaggNTjmT93fJpVTthVDYBRXndx",
            "DZREETafG2OoKiEaBbdTeCBqp9BLDY3H",
            "NvcpCqZZsylufb9SHliBXUty5lEV8Cws",
            "OFJ20SY5j7pMyIRza1cZfqQfxOFiDmIG"
        ],
        "ratingCount": 529,
        "openingPeriods": [
            {
                "open": {
                    "day": 0,
                    "time": "1000"
                },
                "close": {
                    "day": 0,
                    "time": "1600"
                }
            },
            {
                "open": {
                    "day": 3,
                    "time": "1100"
                },
                "close": {
                    "day": 3,
                    "time": "1600"
                }
            },
            {
                "open": {
                    "day": 4,
                    "time": "1100"
                },
                "close": {
                    "day": 4,
                    "time": "1600"
                }
            },
            {
                "open": {
                    "day": 5,
                    "time": "1100"
                },
                "close": {
                    "day": 5,
                    "time": "1600"
                }
            },
            {
                "open": {
                    "day": 6,
                    "time": "1100"
                },
                "close": {
                    "day": 6,
                    "time": "1600"
                }
            }
        ],
        "name": "Notre-Dame-des-Victoires Catholic Church",
        "permanentlyClosed": false,
        "priceLevel": null,
        "phone": "+1 418-692-1650",
        "address": "32 Rue Sous-le-Fort, Québec City, Quebec G1K 4E8, Canada",
        "types": [
            "Catholic church",
            "Sights & Landmarks",
            "Church",
            "Sacred & Religious Sites"
        ],
        "ratingDistribution": {
            "Google": {
                "1": 8,
                "2": 6,
                "3": 28,
                "4": 110,
                "5": 379
            }
        }
    },
    {
        "placeId": "ChIJkVJUZCKVuEwRQCZNrq0MBAU",
        "website": "http://www.ville.levis.qc.ca/",
        "index": 19,
        "utcOffset": -240,
        "longitude": -71.239715,
        "latitude": 46.758258,
        "rating": null,
        "excerpt": "Lévis is a city in eastern Quebec, Canada, located on the south shore of the St. Lawrence River, opposite Quebec City. A ferry links Old Quebec with Old Lévis, and two bridges, the Quebec Bridge and the Pierre-Laporte Bridge, connect western Lévis with Quebec City.\nThe population in 2021 was 149,683. Wikipedia.",
        "detail_description": "Lévis, situated on the southern bank of the St. Lawrence River in Quebec, Canada, is a charming city with a population of around 149,683. It is connected to Quebec City by a ferry and two bridges - the Quebec Bridge and the Pierre-Laporte Bridge. The ferry ride offers stunning views of both cities and is an excellent opportunity for photography enthusiasts.",
        "imageKeys": [
            "7q4wtm1hAhiL1njOECshbMmdfejGwcHq",
            "6HbGIwo9xpXLhF6i6t9cZpmvyZwrTlMz",
            "pVW8QmeaXkIWthqUMVnbUjjtkpMrlg7D",
            "KC8JWR6WaYhfXAsB7fEIkaR0btOdM8JE",
            "nO7QJdOo92wI7VhBSCm9zrkUYxQe3BVP"
        ],
        "ratingCount": null,
        "openingPeriods": null,
        "name": "Levis",
        "permanentlyClosed": false,
        "priceLevel": null,
        "phone": null,
        "address": "Quebec, Canada",
        "types": [],
        "ratingDistribution": {
            "Google": {
                "1": 0,
                "2": 0,
                "3": 0,
                "4": 0,
                "5": 0
            }
        }
    },
    {
        "placeId": "ChIJLfajeN-VuEwRMdQNGn3uvYk",
        "website": "https://www.pc.gc.ca/fr/lhn-nhs/qc/fortifications/culture/histoire-history/artillerie-artillery",
        "index": 20,
        "utcOffset": -240,
        "longitude": -71.21326,
        "latitude": 46.813628,
        "rating": 4.5,
        "excerpt": "Former barracks, prison & foundry, open in summer for guided tours & battle reenactments.",
        "detail_description": "Artillery Park is a historical site in Quebec City that offers guided tours and battle reenactments during the summer. The park encompasses various significant structures such as the mills redoubt, Mont-Carmel Park, Esplanade powder magazine, Artillery barracks, and more. It provides insights into the history of French and British troops from 1712 to the end of the 20th century.",
        "imageKeys": [
            "djXvYuKC92aYE400fHN8aUrcbR6L2cQ7",
            "bFpKdxcE2c4LsQIAnzKW8Qv3RBaFMKH3",
            "NvEQj2PIQJ5DxLJuzl6TH5my9RqNjNuP",
            "Fc8W9vJfYrXATwlc8Pi3M4ucNySLYwpo",
            "28Kc6KYnTpQVVcTvthlO8yxRpHNZVXGu"
        ],
        "ratingCount": 354,
        "openingPeriods": [
            {
                "open": {
                    "day": 0,
                    "time": "0930"
                },
                "close": {
                    "day": 0,
                    "time": "1700"
                }
            },
            {
                "open": {
                    "day": 1,
                    "time": "0930"
                },
                "close": {
                    "day": 1,
                    "time": "1700"
                }
            },
            {
                "open": {
                    "day": 2,
                    "time": "0930"
                },
                "close": {
                    "day": 2,
                    "time": "1700"
                }
            },
            {
                "open": {
                    "day": 3,
                    "time": "0930"
                },
                "close": {
                    "day": 3,
                    "time": "1700"
                }
            },
            {
                "open": {
                    "day": 4,
                    "time": "0930"
                },
                "close": {
                    "day": 4,
                    "time": "1700"
                }
            },
            {
                "open": {
                    "day": 5,
                    "time": "0930"
                },
                "close": {
                    "day": 5,
                    "time": "1700"
                }
            },
            {
                "open": {
                    "day": 6,
                    "time": "0930"
                },
                "close": {
                    "day": 6,
                    "time": "1700"
                }
            }
        ],
        "name": "Artillery Park",
        "permanentlyClosed": false,
        "priceLevel": null,
        "phone": "(888) 773-8888",
        "address": "2 Rue D'Auteuil, Québec City, Quebec G1R 5C2, Canada",
        "types": [
            "Historical landmark",
            "Sights & Landmarks",
            "Tour agency",
            "Historic Sites"
        ],
        "ratingDistribution": {
            "Google": {
                "1": 3,
                "2": 3,
                "3": 30,
                "4": 103,
                "5": 215
            }
        }
    }
]